dblinea/__init__.py
dblinea/db_postgresql.py
dblinea/dblinea.py
dblinea/queryset.py
dblinea/scienceserver.py
dblinea/table.py
dblinea-1.0.0.dist-info/LICENSE
dblinea-1.0.0.dist-info/METADATA
dblinea-1.0.0.dist-info/WHEEL
dblinea-1.0.0.dist-info/top_level.txt
dblinea-1.0.0.dist-info/RECORD
