Metadata-Version: 2.1
Name: dblinea
Version: 1.0.0
Summary: Python library to access LIneA's database from Python code. Useful to retrieve data inside LIneA's JupyterHub platform.
Home-page: https://github.com/linea-it/dblinea
License: MIT
Requires-Python: >=3.8
License-File: LICENSE
Requires-Dist: sqlalchemy >=2.0.0
Requires-Dist: psycopg2-binary >=2.9.1
Requires-Dist: numpy >=1.19.4
Requires-Dist: pandas >=2.0.0
Requires-Dist: requests >=2.23.0
Requires-Dist: astropy >=5.0.0
